intake_copernicus/__init__.py
intake_copernicus/source.py
intake_copernicus-0.1.1.dist-info/licenses/AUTHORS.rst
intake_copernicus-0.1.1.dist-info/licenses/LICENSE
intake_copernicus-0.1.1.dist-info/METADATA
intake_copernicus-0.1.1.dist-info/WHEEL
intake_copernicus-0.1.1.dist-info/entry_points.txt
intake_copernicus-0.1.1.dist-info/top_level.txt
intake_copernicus-0.1.1.dist-info/RECORD
