Metadata-Version: 2.4
Name: intake_copernicus
Version: 0.1.1
Summary: Intake driver for the Copernicus Marine client
Author-email: Oceanum Developers <developers@oceanum.science>
Maintainer-email: Oceanum Developers <developers@oceanum.science>
License: MIT license
Project-URL: bugs, https://github.com/oceanum/intake_copernicus/issues
Project-URL: changelog, https://github.com/oceanum/intake_copernicus/blob/master/changelog.md
Project-URL: homepage, https://github.com/oceanum/intake_copernicus
License-File: LICENSE
License-File: AUTHORS.rst
Requires-Dist: copernicusmarine
Requires-Dist: intake
Requires-Dist: jinja2
Requires-Dist: typer
Provides-Extra: dev
Requires-Dist: coverage; extra == "dev"
Requires-Dist: ipdb; extra == "dev"
Requires-Dist: ipython; extra == "dev"
Requires-Dist: mypy; extra == "dev"
Requires-Dist: pytest; extra == "dev"
Requires-Dist: ruff; extra == "dev"
Requires-Dist: sphinx; extra == "dev"
Requires-Dist: tox; extra == "dev"
Requires-Dist: twine; extra == "dev"
Dynamic: license-file
